tscluster/__init__.py
tscluster/base.py
tscluster/interface.py
tscluster/greedytscluster/__init__.py
tscluster/greedytscluster/greedytscluster.py
tscluster/metrics/__init__.py
tscluster/metrics/metrics.py
tscluster/opttscluster/__init__.py
tscluster/opttscluster/optcluster.py
tscluster/opttscluster/opttscluster.py
tscluster/preprocessing/__init__.py
tscluster/preprocessing/interface.py
tscluster/preprocessing/scaler.py
tscluster/preprocessing/utils.py
tscluster/tskmeans/__init__.py
tscluster/tskmeans/tsglobalkmeans.py
tscluster/tskmeans/tskmeans.py
tscluster/tsplot/__init__.py
tscluster/tsplot/tsplot.py
tscluster-1.0.8.dist-info/METADATA
tscluster-1.0.8.dist-info/WHEEL
tscluster-1.0.8.dist-info/top_level.txt
tscluster-1.0.8.dist-info/RECORD
