Metadata-Version: 2.4
Name: tscluster
Version: 1.0.8
Summary: A useful package for temporal clustering
Author: Jolomi Tosanwumi, Jiazhou Liang
Author-email: tjolomi@gmail.com, joe.liang@mail.utoronto.ca
License: MIT
Requires-Dist: numpy>=1.26
Requires-Dist: scipy>=1.10
Requires-Dist: gurobipy>=11.0
Requires-Dist: tslearn>=0.6.3
Requires-Dist: h5py>=3.10
Requires-Dist: pandas>=2.2
Requires-Dist: matplotlib<3.9,>=3.8
Dynamic: author
Dynamic: author-email
Dynamic: description
Dynamic: description-content-type
Dynamic: license
Dynamic: requires-dist
Dynamic: summary
